README.rst
setup.py
rvlm/__init__.py
rvlm.entrypoint.egg-info/PKG-INFO
rvlm.entrypoint.egg-info/SOURCES.txt
rvlm.entrypoint.egg-info/dependency_links.txt
rvlm.entrypoint.egg-info/namespace_packages.txt
rvlm.entrypoint.egg-info/top_level.txt
rvlm/entrypoint/__init__.py
rvlm/entrypoint/entrypoint.py