Metadata-Version: 1.1
Name: rvlm.entrypoint
Version: 0.0.7
Summary: Converts function's signature to getopt-style command line options and arguments.
Home-page: https://bitbucket.org/rvlm/rvlm-entrypoint
Author: Pavel Kretov
Author-email: firegurafiku@gmail.com
License: MIT
Keywords: commandline,argparse,getopt,entrypoint
Platform: UNKNOWN
Classifier: Programming Language :: Python
Classifier: Programming Language :: Python :: 2.6
Classifier: Programming Language :: Python :: 2.7
Classifier: Programming Language :: Python :: 3
Classifier: Development Status :: 2 - Pre-Alpha
Classifier: Environment :: Console
Classifier: Intended Audience :: Developers
Classifier: Intended Audience :: Science/Research
Classifier: Intended Audience :: System Administrators
Classifier: License :: OSI Approved :: MIT License
Classifier: Natural Language :: English
Classifier: Operating System :: POSIX
Classifier: Topic :: Software Development :: Libraries :: Python Modules
